{
  "name": "Spacious",
  "slug": "spacious",
  "version": "1.0.0",
  "homepage": "https://themegrill.com/themes/spacious/",
  "category": {
    "all": "All",
    "blog": "Blog",
    "business": "Business",
    "ecommerce": "eCommerce",
    "free": "Free"
  },
  "pagebuilder": {
    "elementor": "Elementor"
  },
  "demos": {
    "spacious-free": {
      "title": "Spacious",
      "preview": "https://demo.themegrill.com/spacious/",
      "description": "This is the default Spacious demo for your responsive business website.",
      "template": [
        "spacious",
        "spacious-pro"
      ],
      "category": [
        "all",
        "blog",
        "business",
        "ecommerce",
        "free"
      ],
      "plugins_list": {
        "everest-forms": {
          "name": "Everest Forms",
          "slug": "everest-forms/everest-forms.php"
        },
        "breadcrumb-navxt": {
          "name": "Breadcrumb NavXT",
          "slug": "breadcrumb-navxt/breadcrumb-navxt.php"
        },
        "recent-posts-widget-extended": {
          "name": "Recent Posts Widget Extended",
          "slug": "recent-posts-widget-extended/rpwe.php"
        },
        "woocommerce": {
          "name": "WooCommerce",
          "slug": "woocommerce/woocommerce.php"
        }
      },
      "core_options": {
        "blogname": "Spacious",
        "page_on_front": "Business Template",
        "page_for_posts": "Blog"
      }
    },
    "spacious-blog": {
      "title": "Spacious Blog",
      "preview": "https://demo.themegrill.com/spacious-blog/",
      "description": "Want to start the blog for your business? Use this Spacious demo.",
      "template": [
        "spacious",
        "spacious-pro"
      ],
      "category": [
        "all",
        "blog",
        "free"
      ],
      "pagebuilder": [
        "elementor"
      ],
      "plugins_list": {
        "everest-forms": {
          "name": "Everest Forms",
          "slug": "everest-forms/everest-forms.php"
        },
        "spacious-toolkit": {
          "name": "Spacious Toolkit",
          "slug": "spacious-toolkit/spacious-toolkit.php"
        }
      },
      "core_options": {
        "blogname": "Spacious Blog",
        "page_on_front": "Home"
      }
    },
    "spacious-pro": {
      "isPro": true,
      "title": "Spacious Pro",
      "preview": "https://demo.themegrill.com/spacious-pro/",
      "description": "Enhance your business advantage in your website with this Spacious demo.",
      "template": [
        "spacious-pro"
      ],
      "category": [
        "all",
        "blog",
        "business",
        "ecommerce"
      ],
      "plugins_list": {
        "everest-forms": {
          "name": "Everest Forms",
          "slug": "everest-forms/everest-forms.php"
        },
        "breadcrumb-navxt": {
          "name": "Breadcrumb NavXT",
          "slug": "breadcrumb-navxt/breadcrumb-navxt.php"
        },
        "recent-posts-widget-extended": {
          "name": "Recent Posts Widget Extended",
          "slug": "recent-posts-widget-extended/rpwe.php"
        },
        "woocommerce": {
          "name": "WooCommerce",
          "slug": "woocommerce/woocommerce.php"
        }
      },
      "core_options": {
        "blogname": "Spacious Pro",
        "page_on_front": "Home",
        "page_for_posts": "Blog"
      }
    },
    "spacious-pro-business": {
      "isPro": true,
      "title": "Spacious Pro Business",
      "preview": "http://demo.themegrill.com/spacious-pro-business/",
      "description": "This is the default Spacious demo for your responsive business website.",
      "template": [
        "spacious-pro"
      ],
      "category": [
        "all",
        "business"
      ],
      "pagebuilder": [
        "elementor"
      ],
      "plugins_list": {
        "everest-forms": {
          "name": "Everest Forms",
          "slug": "everest-forms/everest-forms.php"
        },
        "spacious-toolkit": {
          "name": "Spacious Toolkit",
          "slug": "spacious-toolkit/spacious-toolkit.php"
        }
      },
      "core_options": {
        "blogname": "Spacious Pro Business",
        "page_on_front": "Home"
      }
    }
  }
}
